Metadata-Version: 2.1
Name: stringhelp
Version: 7.0
Summary: A small example package made to help you with strings
Home-page: UNKNOWN
Author-email: none@example.com
License: UNKNOWN
Platform: UNKNOWN
Classifier: Programming Language :: Python :: 3
Classifier: License :: OSI Approved :: MIT License
Classifier: Operating System :: OS Independent
Requires-Python: >=3.6
